KotlinZhongwenCankao/README.md
KotlinZhongwenCankao/__init__.py
KotlinZhongwenCankao/__main__.py
KotlinZhongwenCankao/file.epub
KotlinZhongwenCankao/index.html
KotlinZhongwenCankao/css/__init__.py
KotlinZhongwenCankao/css/annotations.css
KotlinZhongwenCankao/css/main.css
KotlinZhongwenCankao/css/normalize.css
KotlinZhongwenCankao/css/popup.css
KotlinZhongwenCankao/font/__init__.py
KotlinZhongwenCankao/font/fontello.eot
KotlinZhongwenCankao/font/fontello.svg
KotlinZhongwenCankao/font/fontello.ttf
KotlinZhongwenCankao/font/fontello.woff
KotlinZhongwenCankao/img/__init__.py
KotlinZhongwenCankao/img/annotator-glyph-sprite.png
KotlinZhongwenCankao/img/annotator-icon-sprite.png
KotlinZhongwenCankao/img/apple-touch-icon.png
KotlinZhongwenCankao/img/cancelfullscreen.png
KotlinZhongwenCankao/img/close.png
KotlinZhongwenCankao/img/fullscreen.png
KotlinZhongwenCankao/img/loader.gif
KotlinZhongwenCankao/img/menu-icon.png
KotlinZhongwenCankao/img/save.png
KotlinZhongwenCankao/img/saved.png
KotlinZhongwenCankao/img/settings-s.png
KotlinZhongwenCankao/img/settings.png
KotlinZhongwenCankao/img/star.png
KotlinZhongwenCankao/js/__init__.py
KotlinZhongwenCankao/js/epub.js
KotlinZhongwenCankao/js/epub.min.js
KotlinZhongwenCankao/js/epub.min.map
KotlinZhongwenCankao/js/hooks.min.js
KotlinZhongwenCankao/js/hooks.min.map
KotlinZhongwenCankao/js/reader.js
KotlinZhongwenCankao/js/reader.js.map
KotlinZhongwenCankao/js/reader.min.js
KotlinZhongwenCankao/js/reader.min.map
KotlinZhongwenCankao/js/hooks/__init__.py
KotlinZhongwenCankao/js/hooks/extensions/__init__.py
KotlinZhongwenCankao/js/hooks/extensions/highlight.js
KotlinZhongwenCankao/js/libs/__init__.py
KotlinZhongwenCankao/js/libs/jquery.min.js
KotlinZhongwenCankao/js/libs/localforage.min.js
KotlinZhongwenCankao/js/libs/screenfull.js
KotlinZhongwenCankao/js/libs/screenfull.min.js
KotlinZhongwenCankao/js/libs/zip.min.js
KotlinZhongwenCankao/js/plugins/__init__.py
KotlinZhongwenCankao/js/plugins/hypothesis.js
kotlin_zhongwen_cankao-2024.3.1.0.dist-info/METADATA
kotlin_zhongwen_cankao-2024.3.1.0.dist-info/WHEEL
kotlin_zhongwen_cankao-2024.3.1.0.dist-info/entry_points.txt
kotlin_zhongwen_cankao-2024.3.1.0.dist-info/top_level.txt
kotlin_zhongwen_cankao-2024.3.1.0.dist-info/RECORD
